referenceseeker/__init__.py
referenceseeker/ani.py
referenceseeker/app.py
referenceseeker/constants.py
referenceseeker/database.py
referenceseeker/mash.py
referenceseeker/util.py
referenceseeker-1.8.0.dist-info/LICENSE
referenceseeker-1.8.0.dist-info/METADATA
referenceseeker-1.8.0.dist-info/WHEEL
referenceseeker-1.8.0.dist-info/entry_points.txt
referenceseeker-1.8.0.dist-info/top_level.txt
referenceseeker-1.8.0.dist-info/RECORD
