Metadata-Version: 2.1
Name: referenceseeker
Version: 1.8.0
Summary: ReferenceSeeker: rapid determination of appropriate reference genomes.
Home-page: https://github.com/oschwengers/referenceseeker
Author: Oliver Schwengers
Author-email: oliver.schwengers@computational.bio.uni-giessen.de
License: GPLv3
Project-URL: Bug Reports, https://github.com/oschwengers/referenceseeker/issues
Project-URL: Source, https://github.com/oschwengers/referenceseeker
Keywords: bioinformatics,ngs,wgs,microbial genomics
Platform: UNKNOWN
Classifier: Operating System :: POSIX :: Linux
Classifier: Programming Language :: Python :: 3 :: Only
Classifier: Development Status :: 5 - Production/Stable
Classifier: License :: OSI Approved :: GNU General Public License v3 (GPLv3)
Classifier: Topic :: Scientific/Engineering :: Bio-Informatics
Classifier: Environment :: Console
Classifier: Intended Audience :: Science/Research
Classifier: Natural Language :: English
Requires-Python: >=3.8
Requires-Dist: biopython (>=1.78)
Requires-Dist: xopen (>=1.1.0)
